MANIFEST.in
README.rst
setup.cfg
setup.py
docs/HISTORY.rst
docs/INSTALL.rst
docs/LICENSE.GPL
docs/LICENSE.txt
platocdp/__init__.py
platocdp.timesheet.egg-info/PKG-INFO
platocdp.timesheet.egg-info/SOURCES.txt
platocdp.timesheet.egg-info/dependency_links.txt
platocdp.timesheet.egg-info/entry_points.txt
platocdp.timesheet.egg-info/namespace_packages.txt
platocdp.timesheet.egg-info/not-zip-safe
platocdp.timesheet.egg-info/paster_plugins.txt
platocdp.timesheet.egg-info/requires.txt
platocdp.timesheet.egg-info/top_level.txt
platocdp/timesheet/__init__.py
platocdp/timesheet/configure.zcml
platocdp/timesheet/interfaces.py
platocdp/timesheet/setuphandlers.py
platocdp/timesheet/behavior/README.txt
platocdp/timesheet/behavior/__init__.py
platocdp/timesheet/behavior/configure.zcml
platocdp/timesheet/browser/README.txt
platocdp/timesheet/browser/__init__.py
platocdp/timesheet/browser/activity_view.py
platocdp/timesheet/browser/timesheetlisting.py
platocdp/timesheet/browser/templates/activity_view.pt
platocdp/timesheet/browser/templates/timesheetlisting.pt
platocdp/timesheet/content/README.txt
platocdp/timesheet/content/__init__.py
platocdp/timesheet/content/activity.py
platocdp/timesheet/locales/README.txt
platocdp/timesheet/portlet/__init__.py
platocdp/timesheet/portlet/configure.zcml
platocdp/timesheet/profiles/default/browserlayer.xml
platocdp/timesheet/profiles/default/cssregistry.xml
platocdp/timesheet/profiles/default/jsregistry.xml
platocdp/timesheet/profiles/default/metadata.xml
platocdp/timesheet/profiles/default/platocdp.timesheet.marker.txt
platocdp/timesheet/profiles/default/portlets.xml
platocdp/timesheet/profiles/default/types.xml
platocdp/timesheet/profiles/default/types/platocdp.timesheet.activity.xml
platocdp/timesheet/schemaextender/__init__.py
platocdp/timesheet/static/README.txt
platocdp/timesheet/upgrades/__init__.py
platocdp/timesheet/upgrades/handlers.py
platocdp/timesheet/upgrades/profiles.py
platocdp/timesheet/viewlet/__init__.py
platocdp/timesheet/vocabulary/__init__.py