Metadata-Version: 1.1
Name: platocdp.timesheet
Version: 0.1a1
Summary: Simple Timesheet for PlatoCDP
Home-page: http://github.com/koslab/platocdp.timesheet
Author: KOSLAB Technologies
Author-email: izhar@koslab.org
License: gpl
Platform: UNKNOWN
Classifier: Framework :: Plone
Classifier: Programming Language :: Python
Classifier: Topic :: Software Development :: Libraries :: Python Modules
